simplestr/__init__.py
simplestr/simplestr.py
simplestr/tests/__init__.py
simplestr/tests/test_all.py
simplestr-0.5.0.dist-info/LICENSE.txt
simplestr-0.5.0.dist-info/METADATA
simplestr-0.5.0.dist-info/WHEEL
simplestr-0.5.0.dist-info/top_level.txt
simplestr-0.5.0.dist-info/RECORD
