Metadata-Version: 2.1
Name: simplestr
Version: 0.5.0
Summary: Simple annotations to automatically generate __str__(self), __repr__(self) and __eq__(self, other) methods in classes
Home-page: https://github.com/jpleorx/simplestr
Author: Leo Ertuna
Author-email: leo.ertuna@gmail.com
License: Creative Commons Attribution-NonCommercial-NoDerivatives 4.0 International Public License
Download-URL: https://pypi.org/project/simplestr/
Keywords: str,repr,eq,generate,automatic,annotation
Platform: UNKNOWN
